{
    "report_data": "12/07/2026 05:19",
    "tornei": [
        {
            "url": "https://www.fitp.it/Tornei/Dettaglio-Competizione.html?competitionId=C4991FE7-4E10-4DE2-9BFC-801A429E182B",
            "nomeTorneo": "BT PAY - TORNEO SERALE - BY SPORFIE",
            "data": "12/07/2026",
            "partite": [
                "Tabellone non disponibile"
            ]
        },
        {
            "url": "https://www.fitp.it/Tornei/Dettaglio-Competizione.html?competitionId=993C397C-10FB-4FF2-BAE6-1CB39E43BAA2",
            "nomeTorneo": "CLUB NOMENTANO - CIRCUITO \"I SERALI DI ROMA\" - IV E III CAT. SINGOLI E DOPPI VIALE ROUSSEAU, 124, 00137 ROMA RM",
            "data": "12/07/2026",
            "partite": [
                "Tabellone non disponibile"
            ]
        }
    ]
}