{
    "tornei": [
        {
            "torneo": "/Tornei/Dettaglio-Competizione.html?competitionId=BD2BFE3D-3293-4127-B58E-54EDDC268A81",
            "categoria": "CIRCUITO OPEN PARCO DEGLI ACQUEDOTTI 2026",
            "tabellone": "Singolare Maschile Open",
            "iscritti": [
                "SIMONE MIRIELLO2.8",
                "GIORGIO ZAPPALÀ4.5",
                "STEFANO MARTONE4.1",
                "ROMAN BARBARULO3.5",
                "MARCO CAVALLARO4.NC",
                "FLAVIO CAPUTO4.5",
                "LEONARDO PINTA4.2",
                "MATTIA CESARINI4.4",
                "FEDERICO JAMES GRISANZIO4.4",
                "GABRIELE MULIERE4.5",
                "FABIO MASALA4.3",
                "FRANCESCO FORTUNATO3.1",
                "ENRICO BENTIVOGLIO4.1",
                "DANYLO SILCHUK3.1",
                "FEDERICO BERTELLI4.2",
                "MAURO BELLI4.5",
                "GIOVANNI PARDO3.2",
                "MALO DE PASTOR4.NC",
                "STEFANO PIETRONIRO4.4",
                "LORIS MENCARELLI2.7",
                "GIANPAOLO VANGI2.8",
                "JACOPO FUSO4.4",
                "DAVIDE GRIMALDI4.6",
                "DONATO MESSINEO4.5",
                "FILIPPO SALVUCCI4.3",
                "SERGIO BELTRANI4.3",
                "ANDREA CERBO2.7",
                "GABRIELE  TIROCCHI4.2",
                "RAFFAELE LIGUORI4.2",
                "EDOARDO SAMELA4.3",
                "DAMIANO LATINI3.4",
                "RICCARDO ARMATI4.4",
                "ALESSANDRO MARTUCCI4.1",
                "FLAVIO AVENIA4.4",
                "SIMONE BARTUCCIO 3.5",
                "ANDREA BIASINI4.1",
                "FLAVIO BINNI2.7",
                "DIEGO ERNESTO PAOLINO4.2",
                "GIANLUCA LODDI4.1",
                "AUGUSTO LONGATTI3.4",
                "MICHELE CATALUDDI4.2",
                "RICCARDO D'AZZEO3.5",
                "LUIGI PACIFICI4.2",
                "ANDREA PERRI2.8",
                "FABIO GERLINI4.2",
                "MATTEO PASTORE3.5",
                "DANIELE CLEMENTE4.2",
                "LORENZO PALCICH3.2",
                "ALESSANDRO BAIA2.8",
                "GABRIELE MARAVIGLIA3.1",
                "AKASH SAMARASINGHALAGE3.4",
                "LEONARDO CARRARETTO2.8",
                "ALESSANDRO MASTROMARINO2.8",
                "LUCIO FERRARO2.8"
            ]
        },
        {
            "torneo": "/Tornei/Dettaglio-Competizione.html?competitionId=BD2BFE3D-3293-4127-B58E-54EDDC268A81",
            "categoria": "CIRCUITO OPEN PARCO DEGLI ACQUEDOTTI 2026",
            "tabellone": "Singolare Femminile Open",
            "iscritti": [
                "ELEONORA BARONI2.6",
                "CLAUDIA BIELLI2.8",
                "EMMA GRAZIANI3.4",
                "AZZURRA STELLABOTTE3.2",
                "KATIA MOLINARI4.1",
                "MICHELA PENTENE'2.7",
                "NICOLE POLANO2.8",
                "NICOLE DI BISCEGLIA2.7",
                "MARA ANGELINI4.2",
                "MARTINA TOZZI2.7",
                "GIULIA LA PORTA2.5",
                "VALENTINA VECCIARELLI2.8",
                "ASIA ZAMMARANO2.8",
                "CHIARA MASSI2.7",
                "ANNA PARISI2.8",
                "LINDA FORMICHETTI4.1",
                "ALESSANDRA PIERETTI3.5",
                "VITTORIA MOLINARI2.8",
                "MARIA COSTANZA MATRANGA2.8",
                "LIVIA PALMA2.8",
                "ANGELICA LODI2.8",
                "LUDOVICA BARONI2.8",
                "BARBARA CAFARO2.8",
                "EMMA SERENI2.6",
                "FABIANA DI MONDA2.8",
                "SOFIA FARSETTI2.8",
                "MARTINA SLAV2.7"
            ]
        }
    ]
}