{
    "report_data": "22/07/2026 19:43",
    "tornei": [
        {
            "url": "https://www.fitp.it/Tornei/Dettaglio-Competizione.html?competitionId=3DE8347A-8501-4DB3-A4C6-4AA955C2151B",
            "nomeTorneo": "17° CIRCUITO DEI CASTELLI ROMANI E DEI MONTI LEPINI 3^/4^ CAT. M/F - 5^ TAPPA",
            "data": "22/07/2026",
            "partite": [
                "Tabellone non disponibile"
            ]
        },
        {
            "url": "https://www.fitp.it/Tornei/Dettaglio-Competizione.html?competitionId=06BD92BE-2D88-4F70-A1C9-B333EC2AB32C",
            "nomeTorneo": "9° TORNEO SERALE 3/4 CAT. M/F",
            "data": "22/07/2026",
            "partite": [
                "Tabellone non disponibile"
            ]
        },
        {
            "url": "https://www.fitp.it/Tornei/Dettaglio-Competizione.html?competitionId=A77405F1-6322-4E39-B06C-9C66A5D54D07",
            "nomeTorneo": "6 TORNEO SERALE M E F",
            "data": "22/07/2026",
            "partite": [
                "Tabellone non disponibile"
            ]
        },
        {
            "url": "https://www.fitp.it/Tornei/Dettaglio-Competizione.html?competitionId=04BEC7CD-0348-4388-A7DB-AF26B8BD4897",
            "nomeTorneo": "VI° TAPPA \"SUMMER IV ROMA\" (LIM 4.1 M/F) - SINGOLI E DOPPI - SERALE",
            "data": "22/07/2026",
            "partite": [
                "Tabellone non disponibile"
            ]
        },
        {
            "url": "https://www.fitp.it/Tornei/Dettaglio-Competizione.html?competitionId=580BB429-EC53-4736-8BD4-5C6E59E4EA7E",
            "nomeTorneo": "8° TROFEO CANOTTIERI LAZIO €5000",
            "data": "22/07/2026",
            "partite": [
                "Tabellone non disponibile"
            ]
        },
        {
            "url": "https://www.fitp.it/Tornei/Dettaglio-Competizione.html?competitionId=B4F64F94-7C3E-49F1-9C25-55743A039E15",
            "nomeTorneo": "BT PAY RODEO LUGLIO BY SPORFIE",
            "data": "22/07/2026",
            "partite": [
                "Nessuna partita trovata"
            ]
        },
        {
            "url": "https://www.fitp.it/Tornei/Dettaglio-Competizione.html?competitionId=B4F64F94-7C3E-49F1-9C25-55743A039E15",
            "nomeTorneo": "BT PAY RODEO LUGLIO BY SPORFIE",
            "data": "23/07/2026",
            "partite": [
                "23/07/2026; 00:00; No. Campo 1 (Principale) Campo 2",
                "23/07/2026; 18:00; SAVINI DAVIDE vs FABRIZI FABRIZIO I; MORALES LOPEZ LORENZO TOMAS vs PERFETTO DAVIDE MARIA",
                "23/07/2026; 19:00; ANNIBALE MATTIA vs SAVINI DAVIDE; MORALES LOPEZ LORENZO TOMAS vs PERFETTO DAVIDE MARIA",
                "23/07/2026; 20:00; GUIDI SIMONE vs D; ANNIBALE MATTIA vs SAVINI DAVIDE; MORALES LOPEZ LORENZO TOMAS vs PERFETTO DAVIDE MARIA; COCCO GABRIEL vs PETRELLA FEDERICO",
                "23/07/2026; 21:00; CERQUOZZI MATTIA vs GUIDI SIMONE; ANNIBALE MATTIA vs SAVINI DAVIDE"
            ]
        },
        {
            "url": "https://www.fitp.it/Tornei/Dettaglio-Competizione.html?competitionId=1D7F33EC-36FA-4DC2-B555-7B3D7653B3EA",
            "nomeTorneo": "TYRSENIA SUMMER RODEO 1",
            "data": "22/07/2026",
            "partite": [
                "Tabellone non disponibile"
            ]
        },
        {
            "url": "https://www.fitp.it/Tornei/Dettaglio-Competizione.html?competitionId=73097254-E9BE-4906-95EE-27DFBD5E8AE2",
            "nomeTorneo": "9^ TAPPA I SERALI DI ROMA",
            "data": "22/07/2026",
            "partite": [
                "Tabellone non disponibile"
            ]
        },
        {
            "url": "https://www.fitp.it/Tornei/Dettaglio-Competizione.html?competitionId=33DC3B5C-8BEC-46BE-8A82-04D89A7D8FE4",
            "nomeTorneo": "SUMMER CUP 4 E 3 CAT MASCHILE E FEMMINILE",
            "data": "22/07/2026",
            "partite": [
                "Tabellone non disponibile"
            ]
        },
        {
            "url": "https://www.fitp.it/Tornei/Dettaglio-Competizione.html?competitionId=F4A9DADD-9EB1-48A5-BD53-DAD1365E745F",
            "nomeTorneo": "TYRSENIA SUMMER RODEO 2",
            "data": "22/07/2026",
            "partite": [
                "Tabellone non disponibile"
            ]
        },
        {
            "url": "https://www.fitp.it/Tornei/Dettaglio-Competizione.html?competitionId=B3F0499C-63C2-464F-8CDB-00892996436D",
            "nomeTorneo": "END SUMMER 26 VILLAYORK GIAANICOLO/MONTEVERDE SINGOLI E DOPPI LIM. 3 CAT",
            "data": "22/07/2026",
            "partite": [
                "Tabellone non disponibile"
            ]
        },
        {
            "url": "https://www.fitp.it/Tornei/Dettaglio-Competizione.html?competitionId=2CC18EC4-784A-4E26-8D66-8975417E3267",
            "nomeTorneo": "TORNEO NAZIONALE WHEELCHAIR A GIRONE - VOLCANO SPORTABILIA",
            "data": "22/07/2026",
            "partite": [
                "Tabellone non disponibile"
            ]
        },
        {
            "url": "https://www.fitp.it/Tornei/Dettaglio-Competizione.html?competitionId=ABDCE6BF-5EEE-43E5-B698-7B96526DD94A",
            "nomeTorneo": "TORNEO SERALE 3 E 4 CAT SINGOLI E DOPPI",
            "data": "22/07/2026",
            "partite": [
                "Tabellone non disponibile"
            ]
        },
        {
            "url": "https://www.fitp.it/Tornei/Dettaglio-Competizione.html?competitionId=A600C002-7DCF-42F1-A6E8-45C23469C2EF",
            "nomeTorneo": "SUMMER IV ROMA",
            "data": "22/07/2026",
            "partite": [
                "Tabellone non disponibile"
            ]
        },
        {
            "url": "https://www.fitp.it/Tornei/Dettaglio-Competizione.html?competitionId=D29A4D12-5085-46C5-85FE-BB537AB7BEC9",
            "nomeTorneo": "MEMORIAL \"GIANVITTORIO MARTINO\" TORNEO OPEN CAT M & F CON MONTEPREMI 4500 €",
            "data": "22/07/2026",
            "partite": [
                "Tabellone non disponibile"
            ]
        },
        {
            "url": "https://www.fitp.it/Tornei/Dettaglio-Competizione.html?competitionId=501DCC43-5FF4-482D-A635-1A6A54C511DC",
            "nomeTorneo": "4^ TAPPA OPEN DECATHLON TENNIS CUP",
            "data": "22/07/2026",
            "partite": [
                "Tabellone non disponibile"
            ]
        },
        {
            "url": "https://www.fitp.it/Tornei/Dettaglio-Competizione.html?competitionId=29746284-AA74-4122-8F0E-A1E737B73C3D",
            "nomeTorneo": "CT EUR - CIRCUITO \"I SERALI DI ROMA\" - 10° TAPPA - IV E III CAT. SINGOLI E DOPPI",
            "data": "22/07/2026",
            "partite": [
                "Tabellone non disponibile"
            ]
        },
        {
            "url": "https://www.fitp.it/Tornei/Dettaglio-Competizione.html?competitionId=5E2CB1A7-3935-4477-A7AF-DAC31F81A27D",
            "nomeTorneo": "17° CIRCUITO DEI CASTELLI ROMANI E DEI MONTI LEPINI 3^/4^ CAT. M/F - 4^ TAPPA",
            "data": "22/07/2026",
            "partite": [
                "22/07/2026; 00:00; No. Campo 1 Campo 2",
                "22/07/2026; 17:00; 1 FRATARCANGELI VALERIO vs CAMILLI ALESSANDRO I; 1 SEMERANO ADRIANO vs VALCARENGHI LEONARDO"
            ]
        },
        {
            "url": "https://www.fitp.it/Tornei/Dettaglio-Competizione.html?competitionId=5E2CB1A7-3935-4477-A7AF-DAC31F81A27D",
            "nomeTorneo": "17° CIRCUITO DEI CASTELLI ROMANI E DEI MONTI LEPINI 3^/4^ CAT. M/F - 4^ TAPPA",
            "data": "23/07/2026",
            "partite": [
                "23/07/2026; 00:00; No. Campo 1 Campo 2",
                "23/07/2026; 17:00; 1 ROSATI LORENZO vs CHIATRONI ANDREA",
                "23/07/2026; 18:30; 1 SEMERANO ADRIANO vs MASSA MAURIZIO"
            ]
        },
        {
            "url": "https://www.fitp.it/Tornei/Dettaglio-Competizione.html?competitionId=FA92DCE1-E29D-4E21-A449-D12BBBCD32C5",
            "nomeTorneo": "9000€ - TERRACINA OPEN SANDRO MARI BY ORIZZONTE - TAB 40 SINGOLARE MASCHILE - SPORTING QUADRIFOGLIO - VIALE EUROPA, 214, 04019 TERRACINA LT",
            "data": "22/07/2026",
            "partite": [
                "Tabellone non disponibile"
            ]
        },
        {
            "url": "https://www.fitp.it/Tornei/Dettaglio-Competizione.html?competitionId=8D6C0C28-4C72-4716-8B08-175B1AAEE5B5",
            "nomeTorneo": "9° ED FERRAGOSTO OPEN \" I SERALI MC DONALD'S\"",
            "data": "22/07/2026",
            "partite": [
                "Tabellone non disponibile"
            ]
        },
        {
            "url": "https://www.fitp.it/Tornei/Dettaglio-Competizione.html?competitionId=CD3A69DA-4600-4E10-BDC7-69CF7AAB6715",
            "nomeTorneo": "SERALE SINGOLI E DOPPI SUMMER 26 VILLAYORK GIANICOLO LIM. 3.1",
            "data": "22/07/2026",
            "partite": [
                "Tabellone non disponibile"
            ]
        },
        {
            "url": "https://www.fitp.it/Tornei/Dettaglio-Competizione.html?competitionId=143EF5AE-732D-4548-A7F9-DC6D67DDC6CE",
            "nomeTorneo": "CIRCOLO CANOTTIERI ROMA - CIRCUITO \"I SERALI DI ROMA\" - MEMORIAL PINO ORECCHIO - IV E III CAT. SINGOLI E DOPPI - LUNGOTEVERE FLAMINIO 39, 00196 ROMA RM - ABBIGLIAMENTO BIANCO",
            "data": "22/07/2026",
            "partite": [
                "Tabellone non disponibile"
            ]
        }
    ]
}